RecursiveFeatureSelector/__init__.py
RecursiveFeatureSelector-1.3.8.dist-info/LICENSE.txt
RecursiveFeatureSelector-1.3.8.dist-info/METADATA
RecursiveFeatureSelector-1.3.8.dist-info/WHEEL
RecursiveFeatureSelector-1.3.8.dist-info/top_level.txt
RecursiveFeatureSelector-1.3.8.dist-info/RECORD
